ovos_bus_client/__init__.py
ovos_bus_client/conf.py
ovos_bus_client/hpm.py
ovos_bus_client/message.py
ovos_bus_client/opm.py
ovos_bus_client/scripts.py
ovos_bus_client/send_func.py
ovos_bus_client/session.py
ovos_bus_client/version.py
ovos_bus_client/apis/__init__.py
ovos_bus_client/apis/enclosure.py
ovos_bus_client/apis/gui.py
ovos_bus_client/apis/ocp.py
ovos_bus_client/client/__init__.py
ovos_bus_client/client/client.py
ovos_bus_client/client/collector.py
ovos_bus_client/client/waiter.py
ovos_bus_client/util/__init__.py
ovos_bus_client/util/scheduler.py
ovos_bus_client-1.3.7.dist-info/licenses/LICENSE
ovos_bus_client-1.3.7.dist-info/METADATA
ovos_bus_client-1.3.7.dist-info/WHEEL
ovos_bus_client-1.3.7.dist-info/entry_points.txt
ovos_bus_client-1.3.7.dist-info/top_level.txt
ovos_bus_client-1.3.7.dist-info/RECORD
