Metadata-Version: 2.4
Name: ovos_bus_client
Version: 1.3.7
Summary: OVOS Messagebus Client
Home-page: https://github.com/OpenVoiceOS/ovos-bus-client
Author: JarbasAI
Author-email: jarbas@openvoiceos.com
License: Apache-2.0
Classifier: Development Status :: 4 - Beta
Classifier: Intended Audience :: Developers
Classifier: License :: OSI Approved :: Apache Software License
Classifier: Programming Language :: Python :: 3
License-File: LICENSE
Requires-Dist: ovos-config<3.0.0,>=0.0.12
Requires-Dist: ovos-utils<1.0.0,>=0.8.2
Requires-Dist: websocket-client>=0.54.0
Requires-Dist: pyee<13.0.0,>=8.1.0
Dynamic: author
Dynamic: author-email
Dynamic: classifier
Dynamic: description
Dynamic: description-content-type
Dynamic: home-page
Dynamic: license
Dynamic: license-file
Dynamic: requires-dist
Dynamic: summary
